similarity_sort
