Metadata-Version: 1.0
Name: similarity-sort
Version: 0.0.4
Summary: Modern Factory Similarity Sort
Home-page: https://github.com/modernfactory/similarity-sort
Author: Marcin Szepczynski, Grzegorz Waszkowiak
Author-email: marcin@modernfactory.pl, grzegorz.waszkowiak@modernfactory.pl
License: MIT
Platform: UNKNOWN
